ZEdit/__init__.py
ZEdit/all_modules.py
ZEdit/appdata.py
ZEdit/asset.py
ZEdit/dropshadow.py
ZEdit/engine.py
ZEdit/generate_dark_theme_icons.py
ZEdit/main.py
ZEdit/mainapp.py
ZEdit/remote.py
ZEdit/requirements.txt
ZEdit/rotpoint.py
ZEdit/saver.py
ZEdit/shader.py
ZEdit/style.qss
ZEdit/userenv.py
ZEdit-1.2.1.dist-info/LICENSE
ZEdit-1.2.1.dist-info/METADATA
ZEdit-1.2.1.dist-info/WHEEL
ZEdit-1.2.1.dist-info/top_level.txt
ZEdit-1.2.1.dist-info/RECORD
